spdx_licenses/__init__.py
spdx_licenses/data/licenses_nonobsolete_only.json
spdx_licenses/error.py
spdx_licenses/parse.py
spdx_licenses/scrap.py
spdx_licenses/test.py
spdx_licenses/tmp.py
spdx_licenses/type.py
spdx_licenses-0.1.13.dist-info/LICENSE
spdx_licenses-0.1.13.dist-info/WHEEL
spdx_licenses-0.1.13.dist-info/METADATA
spdx_licenses-0.1.13.dist-info/RECORD
